cu_api/__init__.py
cu_api/_modidx.py
cu_api/companies.py
cu_api/config.py
cu_api/core.py
cu_api/query.py
cu_api/search.py
cu_api/tasks.py
cu_api-0.0.3.dist-info/.ipynb_checkpoints/not-zip-safe-checkpoint
cu_api-0.0.3.dist-info/LICENSE
cu_api-0.0.3.dist-info/METADATA
cu_api-0.0.3.dist-info/WHEEL
cu_api-0.0.3.dist-info/entry_points.txt
cu_api-0.0.3.dist-info/top_level.txt
cu_api-0.0.3.dist-info/RECORD
