Metadata-Version: 2.1
Name: cu-api
Version: 0.0.3
Summary: a fun project
Home-page: https://github.com/cooper-richason/cu_api
Author: Cooper Richason
Author-email: 144618753+cooper-richason@users.noreply.github.com
License: Apache Software License 2.0
Keywords: nbdev jupyter notebook python
Classifier: Development Status :: 4 - Beta
Classifier: Intended Audience :: Developers
Classifier: Natural Language :: English
Classifier: Programming Language :: Python :: 3.7
Classifier: Programming Language :: Python :: 3.8
Classifier: Programming Language :: Python :: 3.9
Classifier: Programming Language :: Python :: 3.10
Classifier: Programming Language :: Python :: 3.11
Classifier: Programming Language :: Python :: 3.12
Classifier: License :: OSI Approved :: Apache Software License
Requires-Python: >=3.7
License-File: LICENSE
Requires-Dist: pandas
Requires-Dist: requests
Requires-Dist: tqdm
Provides-Extra: dev
Requires-Dist: pandas ; extra == 'dev'
Requires-Dist: requests ; extra == 'dev'
Requires-Dist: tqdm ; extra == 'dev'
